anyv_registers/__init__.py
anyv_registers/anyv_registers.py
anyv_registers/templates/__init__.py
anyv_registers/templates/registerBank.sv.j2
anyv_registers-0.1.0.dist-info/LICENSE
anyv_registers-0.1.0.dist-info/METADATA
anyv_registers-0.1.0.dist-info/WHEEL
anyv_registers-0.1.0.dist-info/entry_points.txt
anyv_registers-0.1.0.dist-info/top_level.txt
anyv_registers-0.1.0.dist-info/RECORD
